example_package/__init__.py
example_package/example.py
ctp_go-0.0.1.dist-info/LICENSE
ctp_go-0.0.1.dist-info/METADATA
ctp_go-0.0.1.dist-info/WHEEL
ctp_go-0.0.1.dist-info/top_level.txt
ctp_go-0.0.1.dist-info/RECORD
