Metadata-Version: 2.1
Name: ctp-go
Version: 0.0.1
Summary: cpt
Home-page: https://github.com/zpx88688/ctpGo
Author: zpx88688
Author-email: zuopeixi8636@foxmail.com
License: UNKNOWN
Project-URL: Bug Tracker, https://github.com/pypa/sampleproject/issues
Platform: UNKNOWN
Classifier: Programming Language :: Python :: 3
Classifier: License :: OSI Approved :: MIT License
Classifier: Operating System :: OS Independent
Requires-Python: >=3.9
License-File: LICENSE
